devhub/__init__.py
devhub/cli.py
devhub/core/__init__.py
devhub/core/config.py
devhub/core/plugin_manager.py
devhub/plugins/__init__.py
devhub/plugins/api/__init__.py
devhub/plugins/format/__init__.py
devhub/utils/__init__.py
devhub/utils/exceptions.py
devhub/utils/logger.py
devhub_tools-1.0.0.dist-info/licenses/LICENSE
devhub_tools-1.0.0.dist-info/METADATA
devhub_tools-1.0.0.dist-info/WHEEL
devhub_tools-1.0.0.dist-info/entry_points.txt
devhub_tools-1.0.0.dist-info/top_level.txt
devhub_tools-1.0.0.dist-info/RECORD
