Metadata-Version: 2.4
Name: devhub-tools
Version: 1.0.0
Summary: The Swiss Army Knife for Developers - A comprehensive CLI toolkit
Author-email: DevHub Team <hello@devhub.dev>
Maintainer-email: DevHub Team <hello@devhub.dev>
License-Expression: MIT
Project-URL: Homepage, https://github.com/arafat-mahmud/Developer-Utilities-Hub
Project-URL: Documentation, https://github.com/arafat-mahmud/Developer-Utilities-Hub/blob/main/README.md
Project-URL: Repository, https://github.com/arafat-mahmud/Developer-Utilities-Hub.git
Project-URL: Bug Tracker, https://github.com/arafat-mahmud/Developer-Utilities-Hub/issues
Project-URL: Changelog, https://github.com/arafat-mahmud/Developer-Utilities-Hub/blob/main/CHANGELOG.md
Project-URL: Discussions, https://github.com/arafat-mahmud/Developer-Utilities-Hub/discussions
Keywords: cli,developer-tools,utilities,devops,automation,formatting,git,api-testing,security,data-conversion
Classifier: Development Status :: 5 - Production/Stable
Classifier: Environment :: Console
Classifier: Intended Audience :: Developers
Classifier: Operating System :: OS Independent
Classifier: Programming Language :: Python :: 3
Classifier: Programming Language :: Python :: 3.8
Classifier: Programming Language :: Python :: 3.9
Classifier: Programming Language :: Python :: 3.10
Classifier: Programming Language :: Python :: 3.11
Classifier: Programming Language :: Python :: 3.12
Classifier: Topic :: Software Development :: Libraries :: Python Modules
Classifier: Topic :: Utilities
Classifier: Topic :: System :: Systems Administration
Requires-Python: >=3.8
License-File: LICENSE
Requires-Dist: click>=8.0.0
Requires-Dist: rich>=13.0.0
Requires-Dist: typer>=0.9.0
Requires-Dist: requests>=2.31.0
Requires-Dist: GitPython>=3.1.0
Requires-Dist: psutil>=5.9.0
Requires-Dist: cryptography>=41.0.0
Requires-Dist: pandas>=2.0.0
Requires-Dist: pyyaml>=6.0.0
Requires-Dist: black>=23.0.0
Requires-Dist: isort>=5.12.0
Requires-Dist: autopep8>=2.0.0
Requires-Dist: libcst>=1.0.0
Requires-Dist: validators>=0.22.0
Requires-Dist: httpx>=0.24.0
Requires-Dist: beautifulsoup4>=4.12.0
Requires-Dist: jsonschema>=4.19.0
Requires-Dist: toml>=0.10.2
Requires-Dist: colorama>=0.4.6
Requires-Dist: tqdm>=4.66.0
Provides-Extra: dev
Requires-Dist: pytest>=7.4.0; extra == "dev"
Requires-Dist: pytest-cov>=4.1.0; extra == "dev"
Requires-Dist: pytest-mock>=3.11.0; extra == "dev"
Requires-Dist: pytest-asyncio>=0.21.0; extra == "dev"
Requires-Dist: mypy>=1.5.0; extra == "dev"
Requires-Dist: ruff>=0.0.291; extra == "dev"
Requires-Dist: pre-commit>=3.4.0; extra == "dev"
Requires-Dist: coverage[toml]>=7.3.0; extra == "dev"
Requires-Dist: bandit>=1.7.5; extra == "dev"
Requires-Dist: safety>=2.3.0; extra == "dev"
Provides-Extra: docs
Requires-Dist: mkdocs>=1.5.0; extra == "docs"
Requires-Dist: mkdocs-material>=9.2.0; extra == "docs"
Requires-Dist: mkdocstrings[python]>=0.23.0; extra == "docs"
Requires-Dist: mkdocs-click>=0.8.0; extra == "docs"
Provides-Extra: test
Requires-Dist: pytest>=7.4.0; extra == "test"
Requires-Dist: pytest-cov>=4.1.0; extra == "test"
Requires-Dist: pytest-mock>=3.11.0; extra == "test"
Requires-Dist: pytest-asyncio>=0.21.0; extra == "test"
Requires-Dist: coverage[toml]>=7.3.0; extra == "test"
Provides-Extra: all
Requires-Dist: devhub-cli[dev,docs,test]; extra == "all"
Dynamic: license-file
